{"102785-000007400120":[{"route_id":"102785-25734_3","trip_id":"102785-159569432","short_name":"6802","arrival":"26:05:00","departure":"26:05:00","headsign":"Lund C"}],"102785-000008600856":[{"route_id":"102785-25734_3","trip_id":"102785-159569250","short_name":"6802","arrival":"26:08:00","departure":"26:08:00","headsign":"København H"}],"102785-000008600857":[{"route_id":"102785-25657_2","trip_id":"102785-159570678","short_name":"802","arrival":"26:04:00","departure":"26:05:00","headsign":"Lund C"},{"route_id":"102785-25657_2","trip_id":"102785-159570512","short_name":"802","arrival":"26:06:00","departure":"26:07:00","headsign":"Østerport"}],"102785-000008600264":[{"route_id":"102785-21348_2","trip_id":"102785-159610541","short_name":"030","arrival":"26:06:00","departure":"26:06:00","headsign":"Silkeborg St."}],"102785-000008600260":[{"route_id":"102785-21348_2","trip_id":"102785-159601649","short_name":"030","arrival":"26:06:00","departure":"26:07:00","headsign":"Aarhus H"},{"route_id":"102785-21348_2","trip_id":"102785-159605105","short_name":"030","arrival":"26:06:00","departure":"26:07:00","headsign":"Aarhus H"}],"102785-000008600263":[{"route_id":"102785-21348_2","trip_id":"102785-159606214","short_name":"030","arrival":"26:05:00","departure":"26:05:00","headsign":"Skanderborg St."}],"102785-000561100101":[{"route_id":"102785-25973_3","trip_id":"102785-159630790","short_name":"3a","arrival":"26:04:00","departure":"26:06:00","headsign":"Gjesing Nord, Thulevej (Esbjerg)"},{"route_id":"102785-25973_3","trip_id":"102785-159630792","short_name":"3a","arrival":"26:04:00","departure":"26:06:00","headsign":"Gjesing Nord, Thulevej (Esbjerg)"},{"route_id":"102785-25973_3","trip_id":"102785-159630795","short_name":"3a","arrival":"26:04:00","departure":"26:06:00","headsign":"Gjesing Nord, Thulevej (Esbjerg)"}],"102785-000561007401":[{"route_id":"102785-25973_3","trip_id":"102785-159630790","short_name":"3a","arrival":"26:07:00","departure":"26:07:00","headsign":"Gjesing Nord, Thulevej (Esbjerg)"},{"route_id":"102785-25973_3","trip_id":"102785-159630792","short_name":"3a","arrival":"26:07:00","departure":"26:07:00","headsign":"Gjesing Nord, Thulevej (Esbjerg)"},{"route_id":"102785-25973_3","trip_id":"102785-159630795","short_name":"3a","arrival":"26:07:00","departure":"26:07:00","headsign":"Gjesing Nord, Thulevej (Esbjerg)"}],"102785-000561007601":[{"route_id":"102785-25973_3","trip_id":"102785-159630790","short_name":"3a","arrival":"26:08:00","departure":"26:08:00","headsign":"Gjesing Nord, Thulevej (Esbjerg)"},{"route_id":"102785-25973_3","trip_id":"102785-159630792","short_name":"3a","arrival":"26:08:00","departure":"26:08:00","headsign":"Gjesing Nord, Thulevej (Esbjerg)"},{"route_id":"102785-25973_3","trip_id":"102785-159630795","short_name":"3a","arrival":"26:08:00","departure":"26:08:00","headsign":"Gjesing Nord, Thulevej (Esbjerg)"}],"102785-000561002342":[{"route_id":"102785-25973_3","trip_id":"102785-159630790","short_name":"3a","arrival":"26:09:00","departure":"26:09:00","headsign":"Gjesing Nord, Thulevej (Esbjerg)"},{"route_id":"102785-25973_3","trip_id":"102785-159630792","short_name":"3a","arrival":"26:09:00","departure":"26:09:00","headsign":"Gjesing Nord, Thulevej (Esbjerg)"},{"route_id":"102785-25973_3","trip_id":"102785-159630795","short_name":"3a","arrival":"26:09:00","departure":"26:09:00","headsign":"Gjesing Nord, Thulevej (Esbjerg)"}],"102785-000561000602":[{"route_id":"102785-25973_3","trip_id":"102785-159630784","short_name":"3a","arrival":"26:05:00","departure":"26:05:00","headsign":"Gjesing Nord, Thulevej (Esbjerg)"}],"102785-000561000502":[{"route_id":"102785-25973_3","trip_id":"102785-159630784","short_name":"3a","arrival":"26:05:30","departure":"26:05:30","headsign":"Gjesing Nord, Thulevej (Esbjerg)"}],"102785-000631207001":[{"route_id":"102785-25003_3","trip_id":"102785-159633966","short_name":"876","arrival":"26:06:00","departure":"26:06:00","headsign":"Fredericia"}],"102785-000631200521":[{"route_id":"102785-25003_3","trip_id":"102785-159633966","short_name":"876","arrival":"26:06:20","departure":"26:06:20","headsign":"Fredericia"}],"102785-000631200511":[{"route_id":"102785-25003_3","trip_id":"102785-159633966","short_name":"876","arrival":"26:06:40","departure":"26:06:40","headsign":"Fredericia"}],"102785-000631200501":[{"route_id":"102785-25003_3","trip_id":"102785-159633966","short_name":"876","arrival":"26:07:00","departure":"26:07:00","headsign":"Fredericia"}],"102785-000631200541":[{"route_id":"102785-25003_3","trip_id":"102785-159633966","short_name":"876","arrival":"26:07:30","departure":"26:07:30","headsign":"Fredericia"}],"102785-000631200551":[{"route_id":"102785-25003_3","trip_id":"102785-159633966","short_name":"876","arrival":"26:08:00","departure":"26:08:00","headsign":"Fredericia"}],"102785-000631200561":[{"route_id":"102785-25003_3","trip_id":"102785-159633966","short_name":"876","arrival":"26:09:00","departure":"26:09:00","headsign":"Fredericia"}],"102785-000631205701":[{"route_id":"102785-25001_3","trip_id":"102785-159633957","short_name":"873","arrival":"26:06:00","departure":"26:06:00","headsign":"Løsning"}],"102785-000631209002":[{"route_id":"102785-25001_3","trip_id":"102785-159633957","short_name":"873","arrival":"26:07:00","departure":"26:07:00","headsign":"Løsning"}],"102785-000631202001":[{"route_id":"102785-25001_3","trip_id":"102785-159633957","short_name":"873","arrival":"26:08:00","departure":"26:08:00","headsign":"Løsning"}],"102785-000561002322":[{"route_id":"102785-23385_3","trip_id":"102785-159630012","short_name":"2a","arrival":"26:05:00","departure":"26:05:00","headsign":"Guldager Byvej v Guldagervej (Esbjerg)"},{"route_id":"102785-23385_3","trip_id":"102785-159630006","short_name":"2a","arrival":"26:05:00","departure":"26:05:00","headsign":"Guldager Byvej v Guldagervej (Esbjerg)"},{"route_id":"102785-23385_3","trip_id":"102785-159630011","short_name":"2a","arrival":"26:05:00","departure":"26:05:00","headsign":"Guldager Byvej v Guldagervej (Esbjerg)"}],"102785-000561008912":[{"route_id":"102785-23385_3","trip_id":"102785-159630012","short_name":"2a","arrival":"26:06:00","departure":"26:06:00","headsign":"Guldager Byvej v Guldagervej (Esbjerg)"},{"route_id":"102785-23385_3","trip_id":"102785-159629999","short_name":"2a","arrival":"26:06:00","departure":"26:06:00","headsign":"Guldager Byvej v Guldagervej (Esbjerg)"},{"route_id":"102785-23385_3","trip_id":"102785-159630006","short_name":"2a","arrival":"26:06:00","departure":"26:06:00","headsign":"Guldager Byvej v Guldagervej (Esbjerg)"},{"route_id":"102785-23385_3","trip_id":"102785-159630011","short_name":"2a","arrival":"26:06:00","departure":"26:06:00","headsign":"Guldager Byvej v Guldagervej (Esbjerg)"}],"102785-000561008902":[{"route_id":"102785-23385_3","trip_id":"102785-159630012","short_name":"2a","arrival":"26:07:00","departure":"26:07:00","headsign":"Guldager Byvej v Guldagervej (Esbjerg)"},{"route_id":"102785-23385_3","trip_id":"102785-159629999","short_name":"2a","arrival":"26:07:00","departure":"26:07:00","headsign":"Guldager Byvej v Guldagervej (Esbjerg)"},{"route_id":"102785-23385_3","trip_id":"102785-159630006","short_name":"2a","arrival":"26:07:00","departure":"26:07:00","headsign":"Guldager Byvej v Guldagervej (Esbjerg)"},{"route_id":"102785-23385_3","trip_id":"102785-159630011","short_name":"2a","arrival":"26:07:00","departure":"26:07:00","headsign":"Guldager Byvej v Guldagervej (Esbjerg)"}],"102785-000561007222":[{"route_id":"102785-23385_3","trip_id":"102785-159630012","short_name":"2a","arrival":"26:08:00","departure":"26:08:00","headsign":"Guldager Byvej v Guldagervej (Esbjerg)"},{"route_id":"102785-23385_3","trip_id":"102785-159629999","short_name":"2a","arrival":"26:08:00","departure":"26:08:00","headsign":"Guldager Byvej v Guldagervej (Esbjerg)"},{"route_id":"102785-23385_3","trip_id":"102785-159630006","short_name":"2a","arrival":"26:08:00","departure":"26:08:00","headsign":"Guldager Byvej v Guldagervej (Esbjerg)"},{"route_id":"102785-23385_3","trip_id":"102785-159630011","short_name":"2a","arrival":"26:08:00","departure":"26:08:00","headsign":"Guldager Byvej v Guldagervej (Esbjerg)"}],"102785-000561006004":[{"route_id":"102785-23385_3","trip_id":"102785-159630012","short_name":"2a","arrival":"26:09:00","departure":"26:09:00","headsign":"Guldager Byvej v Guldagervej (Esbjerg)"},{"route_id":"102785-23385_3","trip_id":"102785-159629999","short_name":"2a","arrival":"26:09:00","departure":"26:09:00","headsign":"Guldager Byvej v Guldagervej (Esbjerg)"},{"route_id":"102785-23385_3","trip_id":"102785-159630006","short_name":"2a","arrival":"26:09:00","departure":"26:09:00","headsign":"Guldager Byvej v Guldagervej (Esbjerg)"},{"route_id":"102785-23385_3","trip_id":"102785-159630011","short_name":"2a","arrival":"26:09:00","departure":"26:09:00","headsign":"Guldager Byvej v Guldagervej (Esbjerg)"}],"102785-000561018802":[{"route_id":"102785-23385_3","trip_id":"102785-159629999","short_name":"2a","arrival":"26:05:00","departure":"26:05:00","headsign":"Guldager Byvej v Guldagervej (Esbjerg)"}],"102785-000561100102":[{"route_id":"102785-23385_3","trip_id":"102785-159629730","short_name":"2a","arrival":"26:07:00","departure":"26:09:00","headsign":"Hedelund (Esbjerg)"},{"route_id":"102785-23385_3","trip_id":"102785-159629639","short_name":"2a","arrival":"26:07:00","departure":"26:09:00","headsign":"Hedelund (Esbjerg)"},{"route_id":"102785-23385_3","trip_id":"102785-159629728","short_name":"2a","arrival":"26:07:00","departure":"26:09:00","headsign":"Hedelund (Esbjerg)"},{"route_id":"102785-23385_3","trip_id":"102785-159629731","short_name":"2a","arrival":"26:07:00","departure":"26:09:00","headsign":"Hedelund (Esbjerg)"}],"102785-000561021951":[{"route_id":"102785-23383_3","trip_id":"102785-159627314","short_name":"1a","arrival":"26:06:00","departure":"26:06:00","headsign":"Kvaglundparken v Egekrattet (Esbjerg)"},{"route_id":"102785-23383_3","trip_id":"102785-159627596","short_name":"1a","arrival":"26:07:00","departure":"26:07:00","headsign":"Kvaglundparken v Egekrattet (Esbjerg)"}],"102785-000561021981":[{"route_id":"102785-23383_3","trip_id":"102785-159627314","short_name":"1a","arrival":"26:07:00","departure":"26:07:00","headsign":"Kvaglundparken v Egekrattet (Esbjerg)"},{"route_id":"102785-23383_3","trip_id":"102785-159627596","short_name":"1a","arrival":"26:08:00","departure":"26:08:00","headsign":"Kvaglundparken v Egekrattet (Esbjerg)"}],"102785-000561021802":[{"route_id":"102785-23383_3","trip_id":"102785-159627314","short_name":"1a","arrival":"26:08:00","departure":"26:08:00","headsign":"Kvaglundparken v Egekrattet (Esbjerg)"},{"route_id":"102785-23383_3","trip_id":"102785-159627742","short_name":"1a","arrival":"26:08:00","departure":"26:08:00","headsign":"Kvaglundparken v Egekrattet (Esbjerg)"},{"route_id":"102785-23383_3","trip_id":"102785-159627596","short_name":"1a","arrival":"26:09:00","departure":"26:09:00","headsign":"Kvaglundparken v Egekrattet (Esbjerg)"}],"102785-000561030202":[{"route_id":"102785-23383_3","trip_id":"102785-159627314","short_name":"1a","arrival":"26:09:00","departure":"26:09:00","headsign":"Kvaglundparken v Egekrattet (Esbjerg)"},{"route_id":"102785-23383_3","trip_id":"102785-159627742","short_name":"1a","arrival":"26:09:00","departure":"26:09:00","headsign":"Kvaglundparken v Egekrattet (Esbjerg)"}],"102785-000561021911":[{"route_id":"102785-23383_3","trip_id":"102785-159627742","short_name":"1a","arrival":"26:05:00","departure":"26:05:00","headsign":"Kvaglundparken v Egekrattet (Esbjerg)"}],"102785-000561021901":[{"route_id":"102785-23383_3","trip_id":"102785-159627742","short_name":"1a","arrival":"26:06:00","departure":"26:06:00","headsign":"Kvaglundparken v Egekrattet (Esbjerg)"}],"102785-000561021921":[{"route_id":"102785-23383_3","trip_id":"102785-159627742","short_name":"1a","arrival":"26:07:00","departure":"26:07:00","headsign":"Kvaglundparken v Egekrattet (Esbjerg)"}],"102785-000561017002":[{"route_id":"102785-23383_3","trip_id":"102785-159627596","short_name":"1a","arrival":"26:05:00","departure":"26:05:00","headsign":"Kvaglundparken v Egekrattet (Esbjerg)"}],"102785-000561018612":[{"route_id":"102785-23383_3","trip_id":"102785-159627596","short_name":"1a","arrival":"26:06:00","departure":"26:06:00","headsign":"Kvaglundparken v Egekrattet (Esbjerg)"}],"102785-000561071802":[{"route_id":"102785-23383_3","trip_id":"102785-159626959","short_name":"1a","arrival":"26:06:00","departure":"26:06:00","headsign":"Bytoften (Esbjerg)"},{"route_id":"102785-23383_3","trip_id":"102785-159627272","short_name":"1a","arrival":"26:07:00","departure":"26:07:00","headsign":"Bytoften (Esbjerg)"},{"route_id":"102785-23383_3","trip_id":"102785-159627244","short_name":"1a","arrival":"26:07:00","departure":"26:07:00","headsign":"Bytoften (Esbjerg)"}],"102785-000561004402":[{"route_id":"102785-23324_3","trip_id":"102785-159625728","short_name":"12","arrival":"26:05:00","departure":"26:05:00","headsign":"Bryndumvej v Landlystvej (Esbjerg)"},{"route_id":"102785-23324_3","trip_id":"102785-159625720","short_name":"12","arrival":"26:09:00","departure":"26:09:00","headsign":"Bryndumvej v Landlystvej (Esbjerg)"},{"route_id":"102785-23324_3","trip_id":"102785-159625731","short_name":"12","arrival":"26:05:00","departure":"26:05:00","headsign":"Bryndumvej v Landlystvej (Esbjerg)"},{"route_id":"102785-23324_3","trip_id":"102785-159625732","short_name":"12","arrival":"26:05:00","departure":"26:05:00","headsign":"Bryndumvej v Landlystvej (Esbjerg)"}],"102785-000561004301":[{"route_id":"102785-23324_3","trip_id":"102785-159625728","short_name":"12","arrival":"26:05:30","departure":"26:05:30","headsign":"Bryndumvej v Landlystvej (Esbjerg)"},{"route_id":"102785-23324_3","trip_id":"102785-159625720","short_name":"12","arrival":"26:09:30","departure":"26:09:30","headsign":"Bryndumvej v Landlystvej (Esbjerg)"},{"route_id":"102785-23324_3","trip_id":"102785-159625731","short_name":"12","arrival":"26:05:30","departure":"26:05:30","headsign":"Bryndumvej v Landlystvej (Esbjerg)"},{"route_id":"102785-23324_3","trip_id":"102785-159625732","short_name":"12","arrival":"26:05:30","departure":"26:05:30","headsign":"Bryndumvej v Landlystvej (Esbjerg)"}],"102785-000561005101":[{"route_id":"102785-23324_3","trip_id":"102785-159625728","short_name":"12","arrival":"26:06:00","departure":"26:06:00","headsign":"Bryndumvej v Landlystvej (Esbjerg)"},{"route_id":"102785-23324_3","trip_id":"102785-159625731","short_name":"12","arrival":"26:06:00","departure":"26:06:00","headsign":"Bryndumvej v Landlystvej (Esbjerg)"},{"route_id":"102785-23324_3","trip_id":"102785-159625732","short_name":"12","arrival":"26:06:00","departure":"26:06:00","headsign":"Bryndumvej v Landlystvej (Esbjerg)"}],"102785-000561005901":[{"route_id":"102785-23324_3","trip_id":"102785-159625728","short_name":"12","arrival":"26:07:00","departure":"26:07:00","headsign":"Bryndumvej v Landlystvej (Esbjerg)"},{"route_id":"102785-23324_3","trip_id":"102785-159625731","short_name":"12","arrival":"26:07:00","departure":"26:07:00","headsign":"Bryndumvej v Landlystvej (Esbjerg)"},{"route_id":"102785-23324_3","trip_id":"102785-159625732","short_name":"12","arrival":"26:07:00","departure":"26:07:00","headsign":"Bryndumvej v Landlystvej (Esbjerg)"}],"102785-000561005911":[{"route_id":"102785-23324_3","trip_id":"102785-159625728","short_name":"12","arrival":"26:08:00","departure":"26:08:00","headsign":"Bryndumvej v Landlystvej (Esbjerg)"},{"route_id":"102785-23324_3","trip_id":"102785-159625731","short_name":"12","arrival":"26:08:00","departure":"26:08:00","headsign":"Bryndumvej v Landlystvej (Esbjerg)"},{"route_id":"102785-23324_3","trip_id":"102785-159625732","short_name":"12","arrival":"26:08:00","departure":"26:08:00","headsign":"Bryndumvej v Landlystvej (Esbjerg)"}],"102785-000561006001":[{"route_id":"102785-23324_3","trip_id":"102785-159625728","short_name":"12","arrival":"26:08:30","departure":"26:08:30","headsign":"Bryndumvej v Landlystvej (Esbjerg)"},{"route_id":"102785-23324_3","trip_id":"102785-159625731","short_name":"12","arrival":"26:08:30","departure":"26:08:30","headsign":"Bryndumvej v Landlystvej (Esbjerg)"},{"route_id":"102785-23324_3","trip_id":"102785-159625732","short_name":"12","arrival":"26:08:30","departure":"26:08:30","headsign":"Bryndumvej v Landlystvej (Esbjerg)"}],"102785-000561006101":[{"route_id":"102785-23324_3","trip_id":"102785-159625728","short_name":"12","arrival":"26:09:00","departure":"26:09:00","headsign":"Bryndumvej v Landlystvej (Esbjerg)"},{"route_id":"102785-23324_3","trip_id":"102785-159625731","short_name":"12","arrival":"26:09:00","departure":"26:09:00","headsign":"Bryndumvej v Landlystvej (Esbjerg)"},{"route_id":"102785-23324_3","trip_id":"102785-159625732","short_name":"12","arrival":"26:09:00","departure":"26:09:00","headsign":"Bryndumvej v Landlystvej (Esbjerg)"}],"102785-000561004131":[{"route_id":"102785-23324_3","trip_id":"102785-159625720","short_name":"12","arrival":"26:07:00","departure":"26:07:00","headsign":"Bryndumvej v Landlystvej (Esbjerg)"}],"102785-000561004201":[{"route_id":"102785-23324_3","trip_id":"102785-159625720","short_name":"12","arrival":"26:08:00","departure":"26:08:00","headsign":"Bryndumvej v Landlystvej (Esbjerg)"}],"102785-000851019101":[{"route_id":"102785-25495_3","trip_id":"102785-159397017","short_name":"27n","arrival":"26:05:00","departure":"26:05:00","headsign":"Uttrup Nord"}],"102785-000851520001":[{"route_id":"102785-25495_3","trip_id":"102785-159397017","short_name":"27n","arrival":"26:06:00","departure":"26:06:00","headsign":"Uttrup Nord"}],"102785-000851011901":[{"route_id":"102785-25495_3","trip_id":"102785-159397017","short_name":"27n","arrival":"26:07:00","departure":"26:07:00","headsign":"Uttrup Nord"}],"102785-000851003401":[{"route_id":"102785-25494_3","trip_id":"102785-159396950","short_name":"26n","arrival":"26:05:00","departure":"26:05:00","headsign":"Hals"}],"102785-000851201401":[{"route_id":"102785-25494_3","trip_id":"102785-159396950","short_name":"26n","arrival":"26:09:00","departure":"26:09:00","headsign":"Hals"}],"102785-000851012601":[{"route_id":"102785-25493_3","trip_id":"102785-159396920","short_name":"25n","arrival":"26:07:00","departure":"26:07:00","headsign":"Storvorde"}],"102785-000851008501":[{"route_id":"102785-25493_3","trip_id":"102785-159396920","short_name":"25n","arrival":"26:08:00","departure":"26:08:00","headsign":"Storvorde"}],"102785-000851805401":[{"route_id":"102785-25493_3","trip_id":"102785-159396920","short_name":"25n","arrival":"26:09:00","departure":"26:09:00","headsign":"Storvorde"}],"102785-000851951901":[{"route_id":"102785-25493_3","trip_id":"102785-159396911","short_name":"25n","arrival":"26:06:00","departure":"26:06:00","headsign":"Dall Villaby"}],"102785-000851102801":[{"route_id":"102785-25493_3","trip_id":"102785-159396911","short_name":"25n","arrival":"26:07:00","departure":"26:07:00","headsign":"Dall Villaby"}],"102785-000851102901":[{"route_id":"102785-25493_3","trip_id":"102785-159396911","short_name":"25n","arrival":"26:07:30","departure":"26:07:30","headsign":"Dall Villaby"}],"102785-000851101501":[{"route_id":"102785-25493_3","trip_id":"102785-159396911","short_name":"25n","arrival":"26:08:00","departure":"26:08:00","headsign":"Dall Villaby"}],"102785-000851935201":[{"route_id":"102785-25493_3","trip_id":"102785-159396911","short_name":"25n","arrival":"26:09:00","departure":"26:09:00","headsign":"Dall Villaby"}],"102785-000851935301":[{"route_id":"102785-25493_3","trip_id":"102785-159396911","short_name":"25n","arrival":"26:09:30","departure":"26:09:30","headsign":"Dall Villaby"}],"102785-000851008401":[{"route_id":"102785-25492_3","trip_id":"102785-159396908","short_name":"24n","arrival":"26:05:00","departure":"26:05:00","headsign":"Universitetet"}],"102785-000851400802":[{"route_id":"102785-25492_3","trip_id":"102785-159396908","short_name":"24n","arrival":"26:06:00","departure":"26:06:00","headsign":"Universitetet"}],"102785-000851401002":[{"route_id":"102785-25492_3","trip_id":"102785-159396908","short_name":"24n","arrival":"26:08:00","departure":"26:08:00","headsign":"Universitetet"}],"102785-000851101103":[{"route_id":"102785-25491_3","trip_id":"102785-159396894","short_name":"23n","arrival":"26:07:00","departure":"26:07:00","headsign":"Visse"}],"102785-000851991601":[{"route_id":"102785-25490_3","trip_id":"102785-159396866","short_name":"22n","arrival":"26:05:00","departure":"26:05:00","headsign":"Gistrup"}],"102785-000851401001":[{"route_id":"102785-25490_3","trip_id":"102785-159396866","short_name":"22n","arrival":"26:07:00","departure":"26:07:00","headsign":"Gistrup"}],"102785-000851400801":[{"route_id":"102785-25490_3","trip_id":"102785-159396866","short_name":"22n","arrival":"26:08:00","departure":"26:08:00","headsign":"Gistrup"}],"102785-000851008601":[{"route_id":"102785-25490_3","trip_id":"102785-159396866","short_name":"22n","arrival":"26:08:30","departure":"26:08:30","headsign":"Gistrup"}],"102785-000851949401":[{"route_id":"102785-25490_3","trip_id":"102785-159396857","short_name":"22n","arrival":"26:05:00","departure":"26:05:00","headsign":"Hasseris"}],"102785-000851949701":[{"route_id":"102785-25490_3","trip_id":"102785-159396857","short_name":"22n","arrival":"26:05:30","departure":"26:05:30","headsign":"Hasseris"}],"102785-000851089101":[{"route_id":"102785-25490_3","trip_id":"102785-159396857","short_name":"22n","arrival":"26:06:00","departure":"26:06:00","headsign":"Hasseris"}],"102785-000851045801":[{"route_id":"102785-25490_3","trip_id":"102785-159396857","short_name":"22n","arrival":"26:08:00","departure":"26:08:00","headsign":"Hasseris"}],"102785-000851804101":[{"route_id":"102785-25489_3","trip_id":"102785-159396849","short_name":"21n","arrival":"26:05:00","departure":"26:05:00","headsign":"Godthåb"}],"102785-000851072301":[{"route_id":"102785-25489_3","trip_id":"102785-159396849","short_name":"21n","arrival":"26:06:00","departure":"26:06:00","headsign":"Godthåb"}],"102785-000851930401":[{"route_id":"102785-25489_3","trip_id":"102785-159396849","short_name":"21n","arrival":"26:08:00","departure":"26:08:00","headsign":"Godthåb"}],"102785-000851930601":[{"route_id":"102785-25489_3","trip_id":"102785-159396849","short_name":"21n","arrival":"26:09:00","departure":"26:09:00","headsign":"Godthåb"}],"102785-000008604111":[{"route_id":"102785-23258_2","trip_id":"102785-159393787","short_name":"75","arrival":"26:07:00","departure":"26:07:00","headsign":"Hjørring St."}],"102785-000008600008":[{"route_id":"102785-23258_2","trip_id":"102785-159393428","short_name":"75","arrival":"26:06:00","departure":"26:06:00","headsign":"Frederikshavn St."},{"route_id":"102785-23258_2","trip_id":"102785-159393453","short_name":"75","arrival":"26:06:00","departure":"26:06:00","headsign":"Frederikshavn St."}],"102785-000008600023":[{"route_id":"102785-23258_2","trip_id":"102785-159393521","short_name":"75","arrival":"26:09:00","departure":"26:09:00","headsign":"Aalborg St."}],"102785-000807300101":[{"route_id":"102785-23090_3","trip_id":"102785-159399957","short_name":"974x","arrival":"26:09:00","departure":"26:09:00","headsign":"Aså Torv"}],"102785-000813100401":[{"route_id":"102785-23089_3","trip_id":"102785-159399893","short_name":"973x","arrival":"26:06:00","departure":"26:06:00","headsign":"Frederikshavn St."}],"102785-000827102401":[{"route_id":"102785-23084_3","trip_id":"102785-159399365","short_name":"950x","arrival":"26:07:00","departure":"26:07:00","headsign":"Løgstør"}],"102785-000813041602":[{"route_id":"102785-23054_3","trip_id":"102785-159398831","short_name":"73n","arrival":"26:05:00","departure":"26:05:00","headsign":"Aalborg St."},{"route_id":"102785-23054_3","trip_id":"102785-159398830","short_name":"73n","arrival":"26:05:00","departure":"26:05:00","headsign":"Aalborg St."}],"102785-000847000102":[{"route_id":"102785-23054_3","trip_id":"102785-159398831","short_name":"73n","arrival":"26:09:00","departure":"26:09:00","headsign":"Aalborg St."},{"route_id":"102785-23054_3","trip_id":"102785-159398830","short_name":"73n","arrival":"26:09:00","departure":"26:09:00","headsign":"Aalborg St."}],"102785-000813041802":[{"route_id":"102785-23054_3","trip_id":"102785-159398831","short_name":"73n","arrival":"26:09:30","departure":"26:09:30","headsign":"Aalborg St."},{"route_id":"102785-23054_3","trip_id":"102785-159398830","short_name":"73n","arrival":"26:09:30","departure":"26:09:30","headsign":"Aalborg St."}],"102785-000851100102":[{"route_id":"102785-23052_3","trip_id":"102785-159398726","short_name":"72n","arrival":"26:05:00","departure":"26:05:00","headsign":"Brønderslev St."}],"102785-000851100701":[{"route_id":"102785-23052_3","trip_id":"102785-159398726","short_name":"72n","arrival":"26:06:00","departure":"26:06:00","headsign":"Brønderslev St."}],"102785-000845200101":[{"route_id":"102785-23003_3","trip_id":"102785-159397996","short_name":"52n","arrival":"26:07:00","departure":"26:07:00","headsign":"Farsø"}],"102785-000845010101":[{"route_id":"102785-23003_3","trip_id":"102785-159397994","short_name":"52n","arrival":"26:05:00","departure":"26:06:00","headsign":"Budolfi Plads via Aalborg St."}],"102785-000845000602":[{"route_id":"102785-23003_3","trip_id":"102785-159397994","short_name":"52n","arrival":"26:08:00","departure":"26:08:00","headsign":"Budolfi Plads via Aalborg St."}],"102785-000008600094":[{"route_id":"102785-26550_2","trip_id":"102785-159587793","short_name":"Rj","arrival":"26:09:00","departure":"26:09:00","headsign":"Praha HL. N st"},{"route_id":"102785-26550_2","trip_id":"102785-159587792","short_name":"Rj","arrival":"26:09:00","departure":"26:09:00","headsign":"Praha HL. N st"}],"102785-000000052968":[{"route_id":"102785-26269_3","trip_id":"102785-159166541","short_name":"Blå","arrival":"26:07:00","departure":"26:07:00","headsign":"Hellerup St. (togbus)"}],"102785-000008651020":[{"route_id":"102785-23839_3","trip_id":"102785-159581074","short_name":"Rød","arrival":"26:06:00","departure":"26:06:00","headsign":"Aalborg St. (togbus)"}],"102785-000000001079":[{"route_id":"102785-22369_3","trip_id":"102785-159166642","short_name":"Rød","arrival":"26:07:00","departure":"26:07:00","headsign":"Nordhavn St. (togbus)"}],"102785-000008600739":[{"route_id":"102785-16453_109","trip_id":"102785-159170805","short_name":"F","arrival":"26:05:00","departure":"26:05:00","headsign":"København Syd St."},{"route_id":"102785-16453_109","trip_id":"102785-159170451","short_name":"F","arrival":"26:09:00","departure":"26:09:00","headsign":"Hellerup St."},{"route_id":"102785-16453_109","trip_id":"102785-159170196","short_name":"F","arrival":"26:09:00","departure":"26:09:00","headsign":"Klampenborg St."},{"route_id":"102785-16452_109","trip_id":"102785-159169975","short_name":"E","arrival":"26:05:00","departure":"26:05:00","headsign":"København Syd St."},{"route_id":"102785-16452_109","trip_id":"102785-159169723","short_name":"E","arrival":"26:09:00","departure":"26:09:00","headsign":"Hillerød St."}],"102785-000008600642":[{"route_id":"102785-16453_109","trip_id":"102785-159170805","short_name":"F","arrival":"26:07:00","departure":"26:07:00","headsign":"København Syd St."},{"route_id":"102785-16453_109","trip_id":"102785-159170451","short_name":"F","arrival":"26:08:00","departure":"26:08:00","headsign":"Hellerup St."},{"route_id":"102785-16453_109","trip_id":"102785-159170196","short_name":"F","arrival":"26:08:00","departure":"26:08:00","headsign":"Klampenborg St."},{"route_id":"102785-16452_109","trip_id":"102785-159169975","short_name":"E","arrival":"26:07:00","departure":"26:07:00","headsign":"København Syd St."},{"route_id":"102785-16452_109","trip_id":"102785-159169723","short_name":"E","arrival":"26:08:00","departure":"26:08:00","headsign":"Hillerød St."}],"102785-000008600640":[{"route_id":"102785-16453_109","trip_id":"102785-159170805","short_name":"F","arrival":"26:08:00","departure":"26:08:00","headsign":"København Syd St."},{"route_id":"102785-16453_109","trip_id":"102785-159170451","short_name":"F","arrival":"26:06:00","departure":"26:06:00","headsign":"Hellerup St."},{"route_id":"102785-16453_109","trip_id":"102785-159170196","short_name":"F","arrival":"26:06:00","departure":"26:06:00","headsign":"Klampenborg St."},{"route_id":"102785-16452_109","trip_id":"102785-159169975","short_name":"E","arrival":"26:08:00","departure":"26:08:00","headsign":"København Syd St."},{"route_id":"102785-16452_109","trip_id":"102785-159169723","short_name":"E","arrival":"26:06:00","departure":"26:06:00","headsign":"Hillerød St."}],"102785-000008600641":[{"route_id":"102785-16453_109","trip_id":"102785-159170451","short_name":"F","arrival":"26:05:00","departure":"26:05:00","headsign":"Hellerup St."},{"route_id":"102785-16453_109","trip_id":"102785-159170196","short_name":"F","arrival":"26:05:00","departure":"26:05:00","headsign":"Klampenborg St."},{"route_id":"102785-16452_109","trip_id":"102785-159169723","short_name":"E","arrival":"26:05:00","departure":"26:05:00","headsign":"Hillerød St."}],"102785-000008600681":[{"route_id":"102785-16452_109","trip_id":"102785-159169786","short_name":"E","arrival":"26:07:00","departure":"26:07:00","headsign":"Hillerød St."},{"route_id":"102785-16448_109","trip_id":"102785-159167046","short_name":"A","arrival":"26:08:00","departure":"26:08:00","headsign":"Hillerød St."}],"102785-000008600711":[{"route_id":"102785-16451_109","trip_id":"102785-159169497","short_name":"C","arrival":"26:06:00","departure":"26:06:00","headsign":"Frederikssund St."}],"102785-000008600956":[{"route_id":"102785-16451_109","trip_id":"102785-159169497","short_name":"C","arrival":"26:08:00","departure":"26:08:00","headsign":"Frederikssund St."}],"102785-000008600645":[{"route_id":"102785-16451_109","trip_id":"102785-159169249","short_name":"C","arrival":"26:05:00","departure":"26:05:00","headsign":"Frederikssund St."},{"route_id":"102785-16448_109","trip_id":"102785-159166981","short_name":"A","arrival":"26:05:00","departure":"26:05:00","headsign":"Østerport St."}],"102785-000008600626":[{"route_id":"102785-16451_109","trip_id":"102785-159169249","short_name":"C","arrival":"26:07:00","departure":"26:08:00","headsign":"Frederikssund St."}],"102785-000008600708":[{"route_id":"102785-16451_109","trip_id":"102785-159169244","short_name":"C","arrival":"26:05:00","departure":"26:05:00","headsign":"Frederikssund St."},{"route_id":"102785-16451_109","trip_id":"102785-159169255","short_name":"C","arrival":"26:05:00","departure":"26:05:00","headsign":"Frederikssund St."}],"102785-000008600709":[{"route_id":"102785-16451_109","trip_id":"102785-159169244","short_name":"C","arrival":"26:08:00","departure":"26:08:00","headsign":"Frederikssund St."},{"route_id":"102785-16451_109","trip_id":"102785-159169255","short_name":"C","arrival":"26:08:00","departure":"26:08:00","headsign":"Frederikssund St."}],"102785-000008600955":[{"route_id":"102785-16451_109","trip_id":"102785-159169244","short_name":"C","arrival":"26:09:00","departure":"26:09:00","headsign":"Frederikssund St."},{"route_id":"102785-16451_109","trip_id":"102785-159169255","short_name":"C","arrival":"26:09:00","departure":"26:09:00","headsign":"Frederikssund St."}],"102785-000008600736":[{"route_id":"102785-16451_109","trip_id":"102785-159168811","short_name":"C","arrival":"26:06:00","departure":"26:06:00","headsign":"Klampenborg St."},{"route_id":"102785-16451_109","trip_id":"102785-159168824","short_name":"C","arrival":"26:06:00","departure":"26:06:00","headsign":"Østerport St."}],"102785-000008600702":[{"route_id":"102785-16451_109","trip_id":"102785-159168811","short_name":"C","arrival":"26:07:00","departure":"26:07:00","headsign":"Klampenborg St."},{"route_id":"102785-16451_109","trip_id":"102785-159168824","short_name":"C","arrival":"26:07:00","departure":"26:07:00","headsign":"Østerport St."}],"102785-000008600701":[{"route_id":"102785-16451_109","trip_id":"102785-159168811","short_name":"C","arrival":"26:09:00","departure":"26:09:00","headsign":"Klampenborg St."},{"route_id":"102785-16451_109","trip_id":"102785-159168824","short_name":"C","arrival":"26:09:00","departure":"26:09:00","headsign":"Østerport St."}],"102785-000008600658":[{"route_id":"102785-16451_109","trip_id":"102785-159168805","short_name":"C","arrival":"26:06:00","departure":"26:06:00","headsign":"Klampenborg St."}],"102785-000008600659":[{"route_id":"102785-16451_109","trip_id":"102785-159168805","short_name":"C","arrival":"26:09:00","departure":"26:09:00","headsign":"Klampenborg St."}],"102785-000008600644":[{"route_id":"102785-16449_109","trip_id":"102785-159168672","short_name":"B","arrival":"26:06:00","departure":"26:06:00","headsign":"Høje Taastrup St."},{"route_id":"102785-16449_109","trip_id":"102785-159168207","short_name":"B","arrival":"26:09:00","departure":"26:09:00","headsign":"Farum St."},{"route_id":"102785-16449_109","trip_id":"102785-159168077","short_name":"B","arrival":"26:09:00","departure":"26:09:00","headsign":"Farum St."}],"102785-000008600654":[{"route_id":"102785-16449_109","trip_id":"102785-159168672","short_name":"B","arrival":"26:09:00","departure":"26:09:00","headsign":"Høje Taastrup St."},{"route_id":"102785-16449_109","trip_id":"102785-159168207","short_name":"B","arrival":"26:07:00","departure":"26:07:00","headsign":"Farum St."},{"route_id":"102785-16449_109","trip_id":"102785-159168077","short_name":"B","arrival":"26:07:00","departure":"26:07:00","headsign":"Farum St."}],"102785-000008600622":[{"route_id":"102785-16449_109","trip_id":"102785-159168610","short_name":"B","arrival":"26:07:00","departure":"26:07:00","headsign":"Høje Taastrup St."},{"route_id":"102785-16449_109","trip_id":"102785-159167978","short_name":"B","arrival":"26:08:00","departure":"26:08:00","headsign":"København H"},{"route_id":"102785-11746_2","trip_id":"102785-159583113","short_name":"Ic","arrival":"26:08:00","departure":"26:08:00","headsign":"CPH Lufthavn"}],"102785-000008600620":[{"route_id":"102785-16449_109","trip_id":"102785-159168516","short_name":"B","arrival":"26:05:00","departure":"26:05:00","headsign":"Høje Taastrup St."}],"102785-000008600798":[{"route_id":"102785-16449_109","trip_id":"102785-159168516","short_name":"B","arrival":"26:08:00","departure":"26:08:00","headsign":"Høje Taastrup St."},{"route_id":"102785-11746_2","trip_id":"102785-159582408","short_name":"Ic","arrival":"26:06:00","departure":"26:07:00","headsign":"CPH Lufthavn"},{"route_id":"102785-11746_2","trip_id":"102785-159583100","short_name":"Ic","arrival":"26:07:00","departure":"26:09:00","headsign":"CPH Lufthavn"},{"route_id":"102785-11746_2","trip_id":"102785-159582454","short_name":"Ic","arrival":"26:06:00","departure":"26:07:00","headsign":"CPH Lufthavn"}],"102785-000008600690":[{"route_id":"102785-16449_109","trip_id":"102785-159168316","short_name":"B","arrival":"26:07:00","departure":"26:07:00","headsign":"Ryparken St."}],"102785-000008600781":[{"route_id":"102785-16449_109","trip_id":"102785-159168316","short_name":"B","arrival":"26:08:00","departure":"26:08:00","headsign":"Ryparken St."}],"102785-000008600696":[{"route_id":"102785-16449_109","trip_id":"102785-159168267","short_name":"B","arrival":"26:05:00","departure":"26:05:00","headsign":"Farum St."},{"route_id":"102785-16449_109","trip_id":"102785-159168137","short_name":"B","arrival":"26:05:00","departure":"26:05:00","headsign":"Farum St."}],"102785-000008600653":[{"route_id":"102785-16449_109","trip_id":"102785-159168207","short_name":"B","arrival":"26:05:00","departure":"26:05:00","headsign":"Farum St."},{"route_id":"102785-16449_109","trip_id":"102785-159168077","short_name":"B","arrival":"26:05:00","departure":"26:05:00","headsign":"Farum St."}],"102785-000008600621":[{"route_id":"102785-16449_109","trip_id":"102785-159167978","short_name":"B","arrival":"26:05:00","departure":"26:05:00","headsign":"København H"}],"102785-000008600790":[{"route_id":"102785-16448_109","trip_id":"102785-159167634","short_name":"A","arrival":"26:08:00","departure":"26:08:00","headsign":"Køge St."}],"102785-000008600791":[{"route_id":"102785-16448_109","trip_id":"102785-159167634","short_name":"A","arrival":"26:09:00","departure":"26:09:00","headsign":"Køge St."}],"102785-000008600764":[{"route_id":"102785-16448_109","trip_id":"102785-159167633","short_name":"A","arrival":"26:06:00","departure":"26:06:00","headsign":"Køge St."},{"route_id":"102785-16448_109","trip_id":"102785-159167510","short_name":"A","arrival":"26:06:00","departure":"26:06:00","headsign":"Køge St."}],"102785-000008600765":[{"route_id":"102785-16448_109","trip_id":"102785-159167633","short_name":"A","arrival":"26:08:00","departure":"26:08:00","headsign":"Køge St."},{"route_id":"102785-16448_109","trip_id":"102785-159167510","short_name":"A","arrival":"26:08:00","departure":"26:08:00","headsign":"Køge St."}],"102785-000008600792":[{"route_id":"102785-16448_109","trip_id":"102785-159167450","short_name":"A","arrival":"26:05:00","departure":"26:05:00","headsign":"Køge St."}],"102785-000008600803":[{"route_id":"102785-16448_109","trip_id":"102785-159167450","short_name":"A","arrival":"26:08:00","departure":"26:08:00","headsign":"Køge St."}],"102785-000008600673":[{"route_id":"102785-16448_109","trip_id":"102785-159167571","short_name":"A","arrival":"26:06:00","departure":"26:06:00","headsign":"Køge St."}],"102785-000008600672":[{"route_id":"102785-16448_109","trip_id":"102785-159167571","short_name":"A","arrival":"26:08:00","departure":"26:08:00","headsign":"Køge St."}],"102785-000008600909":[{"route_id":"102785-16448_109","trip_id":"102785-159167046","short_name":"A","arrival":"26:06:00","departure":"26:06:00","headsign":"Hillerød St."}],"102785-000008600769":[{"route_id":"102785-16448_109","trip_id":"102785-159167045","short_name":"A","arrival":"26:07:00","departure":"26:07:00","headsign":"Hillerød St."},{"route_id":"102785-16448_109","trip_id":"102785-159166940","short_name":"A","arrival":"26:07:00","departure":"26:07:00","headsign":"Østerport St."}],"102785-000008600768":[{"route_id":"102785-16448_109","trip_id":"102785-159167045","short_name":"A","arrival":"26:09:00","departure":"26:09:00","headsign":"Hillerød St."},{"route_id":"102785-16448_109","trip_id":"102785-159166940","short_name":"A","arrival":"26:09:00","departure":"26:09:00","headsign":"Østerport St."}],"102785-000008600646":[{"route_id":"102785-16448_109","trip_id":"102785-159167112","short_name":"A","arrival":"26:06:00","departure":"26:06:00","headsign":"Hillerød St."},{"route_id":"102785-16448_109","trip_id":"102785-159166981","short_name":"A","arrival":"26:07:00","departure":"26:07:00","headsign":"Østerport St."}],"102785-000008600650":[{"route_id":"102785-16448_109","trip_id":"102785-159167112","short_name":"A","arrival":"26:08:00","departure":"26:08:00","headsign":"Hillerød St."}],"102785-000008600054":[{"route_id":"102785-11746_2","trip_id":"102785-159582346","short_name":"Ic","arrival":"26:07:00","departure":"26:07:00","headsign":"Aarhus H"},{"route_id":"102785-11746_2","trip_id":"102785-159582350","short_name":"Ic","arrival":"26:07:00","departure":"26:07:00","headsign":"Aarhus H"},{"route_id":"102785-11746_2","trip_id":"102785-159583069","short_name":"Ic","arrival":"26:07:00","departure":"26:07:00","headsign":"Aalborg Lufthavn St."}],"102785-000008600053":[{"route_id":"102785-11746_2","trip_id":"102785-159582345","short_name":"Ic","arrival":"26:08:00","departure":"26:08:00","headsign":"Aarhus H"},{"route_id":"102785-11746_2","trip_id":"102785-159583063","short_name":"Ic","arrival":"26:08:00","departure":"26:08:00","headsign":"Aalborg Lufthavn St."},{"route_id":"102785-11746_2","trip_id":"102785-159583065","short_name":"Ic","arrival":"26:08:00","departure":"26:08:00","headsign":"Aalborg Lufthavn St."}],"102785-000008600624":[{"route_id":"102785-11746_2","trip_id":"102785-159583134","short_name":"Ic","arrival":"26:07:00","departure":"26:08:00","headsign":"CPH Lufthavn"},{"route_id":"102785-11746_2","trip_id":"102785-159582465","short_name":"Ic","arrival":"26:05:00","departure":"26:07:00","headsign":"CPH Lufthavn"}],"102785-000008600619":[{"route_id":"102785-11746_2","trip_id":"102785-159583103","short_name":"Ic","arrival":"26:05:00","departure":"26:05:00","headsign":"CPH Lufthavn"}],"102785-000008600783":[{"route_id":"102785-11746_2","trip_id":"102785-159582470","short_name":"Ic","arrival":"26:06:00","departure":"26:07:00","headsign":"CPH Lufthavn"}],"102785-000008600611":[{"route_id":"102785-11746_2","trip_id":"102785-159582453","short_name":"Ic","arrival":"26:03:00","departure":"26:05:00","headsign":"CPH Lufthavn"}],"102785-000008600608":[{"route_id":"102785-11746_2","trip_id":"102785-159582455","short_name":"Ic","arrival":"26:03:00","departure":"26:05:00","headsign":"CPH Lufthavn"}],"102785-000779003812":[{"route_id":"102785-26250_3","trip_id":"102785-159644294","short_name":"404s","arrival":"26:06:00","departure":"26:06:00","headsign":"Skive Festivalen/Havnevej (Skive Kom)"}],"102785-000779003802":[{"route_id":"102785-26250_3","trip_id":"102785-159644294","short_name":"404s","arrival":"26:07:00","departure":"26:07:00","headsign":"Skive Festivalen/Havnevej (Skive Kom)"}],"102785-000779000932":[{"route_id":"102785-26250_3","trip_id":"102785-159644294","short_name":"404s","arrival":"26:08:00","departure":"26:08:00","headsign":"Skive Festivalen/Havnevej (Skive Kom)"}],"102785-000779000902":[{"route_id":"102785-26250_3","trip_id":"102785-159644294","short_name":"404s","arrival":"26:09:00","departure":"26:09:00","headsign":"Skive Festivalen/Havnevej (Skive Kom)"}],"102785-000779002101":[{"route_id":"102785-26249_3","trip_id":"102785-159644210","short_name":"402s","arrival":"26:07:00","departure":"26:07:00","headsign":"Skive Festivalen/Havnevej (Skive Kom)"}],"102785-000779008282":[{"route_id":"102785-26249_3","trip_id":"102785-159644210","short_name":"402s","arrival":"26:07:30","departure":"26:07:30","headsign":"Skive Festivalen/Havnevej (Skive Kom)"}],"102785-000779008272":[{"route_id":"102785-26249_3","trip_id":"102785-159644210","short_name":"402s","arrival":"26:08:00","departure":"26:08:00","headsign":"Skive Festivalen/Havnevej (Skive Kom)"}],"102785-000779008252":[{"route_id":"102785-26249_3","trip_id":"102785-159644210","short_name":"402s","arrival":"26:08:30","departure":"26:08:30","headsign":"Skive Festivalen/Havnevej (Skive Kom)"}],"102785-000779008241":[{"route_id":"102785-26249_3","trip_id":"102785-159644210","short_name":"402s","arrival":"26:09:00","departure":"26:09:00","headsign":"Skive Festivalen/Havnevej (Skive Kom)"}],"102785-000779008802":[{"route_id":"102785-25630_3","trip_id":"102785-159648159","short_name":"740s","arrival":"26:05:00","departure":"26:05:00","headsign":"Sparkær"}],"102785-000779008212":[{"route_id":"102785-25627_3","trip_id":"102785-159644476","short_name":"420s","arrival":"26:05:00","departure":"26:05:00","headsign":"Færgen/Branden"}],"102785-000779000309":[{"route_id":"102785-25627_3","trip_id":"102785-159644476","short_name":"420s","arrival":"26:09:00","departure":"26:09:00","headsign":"Færgen/Branden"}],"102785-000779100202":[{"route_id":"102785-25626_3","trip_id":"102785-159644380","short_name":"411s","arrival":"26:05:00","departure":"26:05:00","headsign":"Sønder Ørum"}],"102785-000779000101":[{"route_id":"102785-25626_3","trip_id":"102785-159644381","short_name":"411s","arrival":"26:09:00","departure":"26:09:00","headsign":"Viborg Rtb."}],"102785-000779008202":[{"route_id":"102785-25625_3","trip_id":"102785-159644297","short_name":"40s","arrival":"26:09:00","departure":"26:09:00","headsign":"Thisted St."}],"102785-000779009101":[{"route_id":"102785-25624_3","trip_id":"102785-159637609","short_name":"13s","arrival":"26:05:00","departure":"26:05:00","headsign":"Haderup Rtb. (Herning Kom)"}],"102785-000763002409":[{"route_id":"102785-25624_3","trip_id":"102785-159637609","short_name":"13s","arrival":"26:06:00","departure":"26:06:00","headsign":"Haderup Rtb. (Herning Kom)"}],"102785-000743003001":[{"route_id":"102785-25591_3","trip_id":"102785-159649542","short_name":"860","arrival":"26:06:00","departure":"26:06:00","headsign":"Silkeborg Trafikterminal"}],"102785-000743055204":[{"route_id":"102785-25591_3","trip_id":"102785-159649542","short_name":"860","arrival":"26:08:00","departure":"26:08:00","headsign":"Silkeborg Trafikterminal"}],"102785-000771000109":[{"route_id":"102785-25591_3","trip_id":"102785-159649541","short_name":"860","arrival":"26:08:00","departure":"26:08:00","headsign":"Viborg Rtb."}],"102785-000743031202":[{"route_id":"102785-25589_3","trip_id":"102785-159649421","short_name":"823","arrival":"26:05:00","departure":"26:05:00","headsign":"Silkeborg Trafikterminal"},{"route_id":"102785-23966_3","trip_id":"102785-159636071","short_name":"113","arrival":"26:09:00","departure":"26:09:00","headsign":"Silkeborg Trafikterminal"}],"102785-000743030002":[{"route_id":"102785-25589_3","trip_id":"102785-159649421","short_name":"823","arrival":"26:08:00","departure":"26:08:00","headsign":"Silkeborg Trafikterminal"}],"102785-000615103401":[{"route_id":"102785-24469_3","trip_id":"102785-159649536","short_name":"853","arrival":"26:05:00","departure":"26:05:00","headsign":"Silkeborg Trafikterminal"}],"102785-000615101601":[{"route_id":"102785-24469_3","trip_id":"102785-159649536","short_name":"853","arrival":"26:06:00","departure":"26:06:00","headsign":"Silkeborg Trafikterminal"}],"102785-000615130101":[{"route_id":"102785-24469_3","trip_id":"102785-159649536","short_name":"853","arrival":"26:08:00","departure":"26:08:00","headsign":"Silkeborg Trafikterminal"}],"102785-000749000401":[{"route_id":"102785-24469_3","trip_id":"102785-159649534","short_name":"853","arrival":"26:06:00","departure":"26:06:00","headsign":"Horsens Trafikterminal"}],"102785-000749000411":[{"route_id":"102785-24469_3","trip_id":"102785-159649534","short_name":"853","arrival":"26:06:20","departure":"26:06:20","headsign":"Horsens Trafikterminal"}],"102785-000749001011":[{"route_id":"102785-24469_3","trip_id":"102785-159649534","short_name":"853","arrival":"26:06:40","departure":"26:06:40","headsign":"Horsens Trafikterminal"}],"102785-000749001021":[{"route_id":"102785-24469_3","trip_id":"102785-159649534","short_name":"853","arrival":"26:07:00","departure":"26:07:00","headsign":"Horsens Trafikterminal"}],"102785-000749001001":[{"route_id":"102785-24469_3","trip_id":"102785-159649534","short_name":"853","arrival":"26:08:00","departure":"26:08:00","headsign":"Horsens Trafikterminal"}],"102785-000743016102":[{"route_id":"102785-24258_3","trip_id":"102785-159649657","short_name":"9","arrival":"26:05:00","departure":"26:05:00","headsign":"Silkeborg Trafikterminal"}],"102785-000743016002":[{"route_id":"102785-24258_3","trip_id":"102785-159649657","short_name":"9","arrival":"26:06:00","departure":"26:06:00","headsign":"Silkeborg Trafikterminal"}],"102785-000743000101":[{"route_id":"102785-24258_3","trip_id":"102785-159649657","short_name":"9","arrival":"26:09:00","departure":"26:09:00","headsign":"Silkeborg Trafikterminal"}],"102785-000771000301":[{"route_id":"102785-24217_3","trip_id":"102785-159648136","short_name":"73","arrival":"26:05:00","departure":"26:05:00","headsign":"Silkeborg Trafikterminal"}],"102785-000705000312":[{"route_id":"102785-24217_3","trip_id":"102785-159648136","short_name":"73","arrival":"26:06:00","departure":"26:06:00","headsign":"Silkeborg Trafikterminal"}],"102785-000705000301":[{"route_id":"102785-24217_3","trip_id":"102785-159648136","short_name":"73","arrival":"26:07:00","departure":"26:07:00","headsign":"Silkeborg Trafikterminal"}],"102785-000705000112":[{"route_id":"102785-24217_3","trip_id":"102785-159648136","short_name":"73","arrival":"26:09:00","departure":"26:09:00","headsign":"Silkeborg Trafikterminal"}],"102785-000743042003":[{"route_id":"102785-24159_3","trip_id":"102785-159645845","short_name":"5","arrival":"26:05:00","departure":"26:05:00","headsign":"Silkeborg Trafikterminal"}],"102785-000743042402":[{"route_id":"102785-24159_3","trip_id":"102785-159645845","short_name":"5","arrival":"26:05:30","departure":"26:05:30","headsign":"Silkeborg Trafikterminal"}],"102785-000743042302":[{"route_id":"102785-24159_3","trip_id":"102785-159645845","short_name":"5","arrival":"26:06:00","departure":"26:06:00","headsign":"Silkeborg Trafikterminal"}],"102785-000743042101":[{"route_id":"102785-24159_3","trip_id":"102785-159645845","short_name":"5","arrival":"26:07:00","departure":"26:07:00","headsign":"Silkeborg Trafikterminal"}],"102785-000743041502":[{"route_id":"102785-24159_3","trip_id":"102785-159645845","short_name":"5","arrival":"26:07:30","departure":"26:07:30","headsign":"Silkeborg Trafikterminal"}],"102785-000743041602":[{"route_id":"102785-24159_3","trip_id":"102785-159645845","short_name":"5","arrival":"26:08:00","departure":"26:08:00","headsign":"Silkeborg Trafikterminal"}],"102785-000743041702":[{"route_id":"102785-24159_3","trip_id":"102785-159645845","short_name":"5","arrival":"26:09:00","departure":"26:09:00","headsign":"Silkeborg Trafikterminal"}],"102785-000751460001":[{"route_id":"102785-24149_3","trip_id":"102785-159358922","short_name":"46","arrival":"26:05:00","departure":"26:05:00","headsign":"Natbus Park Allé"}],"102785-000751460103":[{"route_id":"102785-24149_3","trip_id":"102785-159358922","short_name":"46","arrival":"26:06:00","departure":"26:06:00","headsign":"Natbus Park Allé"}],"102785-000751460202":[{"route_id":"102785-24149_3","trip_id":"102785-159358922","short_name":"46","arrival":"26:07:00","departure":"26:07:00","headsign":"Natbus Park Allé"}],"102785-000751460302":[{"route_id":"102785-24149_3","trip_id":"102785-159358922","short_name":"46","arrival":"26:08:00","departure":"26:08:00","headsign":"Natbus Park Allé"}],"102785-000751474902":[{"route_id":"102785-24149_3","trip_id":"102785-159358922","short_name":"46","arrival":"26:09:00","departure":"26:09:00","headsign":"Natbus Park Allé"}],"102785-000751436003":[{"route_id":"102785-24146_3","trip_id":"102785-159358918","short_name":"45","arrival":"26:06:00","departure":"26:06:00","headsign":"Natbus Lystrup"}],"102785-000751437301":[{"route_id":"102785-24146_3","trip_id":"102785-159358918","short_name":"45","arrival":"26:07:00","departure":"26:07:00","headsign":"Natbus Lystrup"}],"102785-000751402803":[{"route_id":"102785-24146_3","trip_id":"102785-159358918","short_name":"45","arrival":"26:08:00","departure":"26:08:00","headsign":"Natbus Lystrup"}],"102785-000751404901":[{"route_id":"102785-24146_3","trip_id":"102785-159358918","short_name":"45","arrival":"26:09:00","departure":"26:09:00","headsign":"Natbus Lystrup"}],"102785-000751420904":[{"route_id":"102785-24141_3","trip_id":"102785-159358825","short_name":"44","arrival":"26:05:00","departure":"26:05:00","headsign":"Natbus Park Allé"}],"102785-000751421004":[{"route_id":"102785-24141_3","trip_id":"102785-159358825","short_name":"44","arrival":"26:06:00","departure":"26:06:00","headsign":"Natbus Park Allé"}],"102785-000751421204":[{"route_id":"102785-24141_3","trip_id":"102785-159358825","short_name":"44","arrival":"26:07:00","departure":"26:07:00","headsign":"Natbus Park Allé"}],"102785-000751421302":[{"route_id":"102785-24141_3","trip_id":"102785-159358825","short_name":"44","arrival":"26:08:00","departure":"26:08:00","headsign":"Natbus Park Allé"}],"102785-000751401602":[{"route_id":"102785-24141_3","trip_id":"102785-159358825","short_name":"44","arrival":"26:09:00","departure":"26:09:00","headsign":"Natbus Park Allé"}],"102785-000751200502":[{"route_id":"102785-24140_3","trip_id":"102785-159358820","short_name":"43","arrival":"26:05:00","departure":"26:05:00","headsign":"Natbus Park Allé"}],"102785-000751405002":[{"route_id":"102785-24140_3","trip_id":"102785-159358820","short_name":"43","arrival":"26:06:00","departure":"26:06:00","headsign":"Natbus Park Allé"}],"102785-000751454902":[{"route_id":"102785-24140_3","trip_id":"102785-159358820","short_name":"43","arrival":"26:08:00","departure":"26:08:00","headsign":"Natbus Park Allé"}],"102785-000751407402":[{"route_id":"102785-24135_3","trip_id":"102785-159358766","short_name":"42","arrival":"26:05:00","departure":"26:05:00","headsign":"Natbus Park Allé"}],"102785-000751475002":[{"route_id":"102785-24135_3","trip_id":"102785-159358766","short_name":"42","arrival":"26:06:00","departure":"26:06:00","headsign":"Natbus Park Allé"}],"102785-000751000702":[{"route_id":"102785-24135_3","trip_id":"102785-159358766","short_name":"42","arrival":"26:07:00","departure":"26:07:00","headsign":"Natbus Park Allé"},{"route_id":"102785-24135_3","trip_id":"102785-159644421","short_name":"42","arrival":"26:07:00","departure":"26:07:00","headsign":"Natbus Park Allé"}],"102785-000751467904":[{"route_id":"102785-24135_3","trip_id":"102785-159358766","short_name":"42","arrival":"26:09:00","departure":"26:09:00","headsign":"Natbus Park Allé"},{"route_id":"102785-24135_3","trip_id":"102785-159644421","short_name":"42","arrival":"26:09:00","departure":"26:09:00","headsign":"Natbus Park Allé"}],"102785-000751445404":[{"route_id":"102785-24135_3","trip_id":"102785-159644421","short_name":"42","arrival":"26:05:00","departure":"26:05:00","headsign":"Natbus Park Allé"}],"102785-000751446204":[{"route_id":"102785-24135_3","trip_id":"102785-159644421","short_name":"42","arrival":"26:06:00","departure":"26:06:00","headsign":"Natbus Park Allé"}],"102785-000751003802":[{"route_id":"102785-24131_3","trip_id":"102785-159358646","short_name":"41","arrival":"26:05:00","departure":"26:05:00","headsign":"Natbus Park Allé"}],"102785-000751413203":[{"route_id":"102785-24131_3","trip_id":"102785-159358646","short_name":"41","arrival":"26:06:00","departure":"26:06:00","headsign":"Natbus Park Allé"}],"102785-000751402202":[{"route_id":"102785-24131_3","trip_id":"102785-159358646","short_name":"41","arrival":"26:07:00","departure":"26:07:00","headsign":"Natbus Park Allé"}],"102785-000751436102":[{"route_id":"102785-24131_3","trip_id":"102785-159358646","short_name":"41","arrival":"26:08:00","departure":"26:08:00","headsign":"Natbus Park Allé"}],"102785-000751403601":[{"route_id":"102785-24131_3","trip_id":"102785-159358646","short_name":"41","arrival":"26:09:00","departure":"26:09:00","headsign":"Natbus Park Allé"}],"102785-000751435001":[{"route_id":"102785-24131_3","trip_id":"102785-159358646","short_name":"41","arrival":"26:09:30","departure":"26:09:30","headsign":"Natbus Park Allé"}],"102785-000751479501":[{"route_id":"102785-24122_3","trip_id":"102785-159358389","short_name":"40","arrival":"26:05:00","departure":"26:05:00","headsign":"Natbus Park Allé"}],"102785-000751479401":[{"route_id":"102785-24122_3","trip_id":"102785-159358389","short_name":"40","arrival":"26:06:00","departure":"26:06:00","headsign":"Natbus Park Allé"}],"102785-000751478101":[{"route_id":"102785-24122_3","trip_id":"102785-159358389","short_name":"40","arrival":"26:07:00","departure":"26:07:00","headsign":"Natbus Park Allé"}],"102785-000751416401":[{"route_id":"102785-24122_3","trip_id":"102785-159358389","short_name":"40","arrival":"26:08:00","departure":"26:08:00","headsign":"Natbus Park Allé"}],"102785-000751416501":[{"route_id":"102785-24122_3","trip_id":"102785-159358389","short_name":"40","arrival":"26:09:00","departure":"26:09:00","headsign":"Natbus Park Allé"}],"102785-000743700502":[{"route_id":"102785-24119_3","trip_id":"102785-159644024","short_name":"4","arrival":"26:05:00","departure":"26:05:00","headsign":"Silkeborg Trafikterminal"}],"102785-000743006202":[{"route_id":"102785-24041_3","trip_id":"102785-159640759","short_name":"215","arrival":"26:06:00","departure":"26:06:00","headsign":"Silkeborg Trafikterminal"}],"102785-000743006102":[{"route_id":"102785-24041_3","trip_id":"102785-159640759","short_name":"215","arrival":"26:07:00","departure":"26:07:00","headsign":"Silkeborg Trafikterminal"}],"102785-000743006002":[{"route_id":"102785-24041_3","trip_id":"102785-159640759","short_name":"215","arrival":"26:07:30","departure":"26:07:30","headsign":"Silkeborg Trafikterminal"}],"102785-000743002902":[{"route_id":"102785-24041_3","trip_id":"102785-159640759","short_name":"215","arrival":"26:08:00","departure":"26:08:00","headsign":"Silkeborg Trafikterminal"}],"102785-000743002102":[{"route_id":"102785-24041_3","trip_id":"102785-159640759","short_name":"215","arrival":"26:09:00","departure":"26:09:00","headsign":"Silkeborg Trafikterminal"}],"102785-000751475602":[{"route_id":"102785-24028_3","trip_id":"102785-159354559","short_name":"200","arrival":"26:06:00","departure":"26:06:00","headsign":"Aarhus"}],"102785-000751300902":[{"route_id":"102785-24028_3","trip_id":"102785-159354559","short_name":"200","arrival":"26:08:00","departure":"26:08:00","headsign":"Aarhus"}],"102785-000713100102":[{"route_id":"102785-24028_3","trip_id":"102785-159354485","short_name":"200","arrival":"26:05:00","departure":"26:05:00","headsign":"Aarhus"}],"102785-000751200302":[{"route_id":"102785-24028_3","trip_id":"102785-159354485","short_name":"200","arrival":"26:07:00","departure":"26:07:00","headsign":"Aarhus"}],"102785-000751202502":[{"route_id":"102785-24028_3","trip_id":"102785-159354485","short_name":"200","arrival":"26:08:00","departure":"26:08:00","headsign":"Aarhus"}],"102785-000751202402":[{"route_id":"102785-24028_3","trip_id":"102785-159354485","short_name":"200","arrival":"26:09:00","departure":"26:09:00","headsign":"Aarhus"}],"102785-000751003302":[{"route_id":"102785-23986_3","trip_id":"102785-159351505","short_name":"123","arrival":"26:05:00","departure":"26:05:00","headsign":"Aarhus Rutebilstation"}],"102785-000751438602":[{"route_id":"102785-23986_3","trip_id":"102785-159351505","short_name":"123","arrival":"26:07:00","departure":"26:07:00","headsign":"Aarhus Rutebilstation"}],"102785-000751000101":[{"route_id":"102785-23986_3","trip_id":"102785-159351505","short_name":"123","arrival":"26:09:00","departure":"26:09:00","headsign":"Aarhus Rutebilstation"}],"102785-000731101302":[{"route_id":"102785-23975_3","trip_id":"102785-159350892","short_name":"118","arrival":"26:05:00","departure":"26:05:00","headsign":"Aarhus Rutebilstation"}],"102785-000731651701":[{"route_id":"102785-23975_3","trip_id":"102785-159350892","short_name":"118","arrival":"26:06:00","departure":"26:06:00","headsign":"Aarhus Rutebilstation"}],"102785-000731101602":[{"route_id":"102785-23975_3","trip_id":"102785-159350892","short_name":"118","arrival":"26:06:30","departure":"26:06:30","headsign":"Aarhus Rutebilstation"}],"102785-000731100702":[{"route_id":"102785-23975_3","trip_id":"102785-159350892","short_name":"118","arrival":"26:07:00","departure":"26:07:00","headsign":"Aarhus Rutebilstation"}],"102785-000731100802":[{"route_id":"102785-23975_3","trip_id":"102785-159350892","short_name":"118","arrival":"26:08:00","departure":"26:08:00","headsign":"Aarhus Rutebilstation"}],"102785-000731800602":[{"route_id":"102785-23975_3","trip_id":"102785-159350892","short_name":"118","arrival":"26:09:00","departure":"26:09:00","headsign":"Aarhus Rutebilstation"}],"102785-000731642001":[{"route_id":"102785-23975_3","trip_id":"102785-159350892","short_name":"118","arrival":"26:09:30","departure":"26:09:30","headsign":"Aarhus Rutebilstation"}],"102785-000711100102":[{"route_id":"102785-23969_3","trip_id":"102785-159350614","short_name":"114","arrival":"26:06:00","departure":"26:06:00","headsign":"Aarhus Rutebilstation"}],"102785-000711100122":[{"route_id":"102785-23969_3","trip_id":"102785-159350614","short_name":"114","arrival":"26:07:00","departure":"26:07:00","headsign":"Aarhus Rutebilstation"}],"102785-000711100112":[{"route_id":"102785-23969_3","trip_id":"102785-159350614","short_name":"114","arrival":"26:08:00","departure":"26:08:00","headsign":"Aarhus Rutebilstation"}],"102785-000743038702":[{"route_id":"102785-23966_3","trip_id":"102785-159636071","short_name":"113","arrival":"26:05:00","departure":"26:05:00","headsign":"Silkeborg Trafikterminal"}],"102785-000751408403":[{"route_id":"102785-23966_3","trip_id":"102785-159636074","short_name":"113","arrival":"26:06:00","departure":"26:06:00","headsign":"Silkeborg Trafikterminal"}],"102785-000751444803":[{"route_id":"102785-23966_3","trip_id":"102785-159636074","short_name":"113","arrival":"26:07:00","departure":"26:07:00","headsign":"Silkeborg Trafikterminal"}],"102785-000751100803":[{"route_id":"102785-23966_3","trip_id":"102785-159636074","short_name":"113","arrival":"26:08:00","departure":"26:08:00","headsign":"Silkeborg Trafikterminal"}],"102785-000703000352":[{"route_id":"102785-23966_3","trip_id":"102785-159350476","short_name":"113","arrival":"26:05:00","departure":"26:05:00","headsign":"Aarhus Rutebilstation"}],"102785-000703000362":[{"route_id":"102785-23966_3","trip_id":"102785-159350476","short_name":"113","arrival":"26:06:00","departure":"26:06:00","headsign":"Aarhus Rutebilstation"},{"route_id":"102785-23966_3","trip_id":"102785-159635964","short_name":"113","arrival":"26:05:00","departure":"26:05:00","headsign":"Aarhus Rutebilstation"}],"102785-000703000302":[{"route_id":"102785-23966_3","trip_id":"102785-159350476","short_name":"113","arrival":"26:07:00","departure":"26:07:00","headsign":"Aarhus Rutebilstation"},{"route_id":"102785-23966_3","trip_id":"102785-159635964","short_name":"113","arrival":"26:06:00","departure":"26:06:00","headsign":"Aarhus Rutebilstation"}],"102785-000703001222":[{"route_id":"102785-23966_3","trip_id":"102785-159350476","short_name":"113","arrival":"26:08:00","departure":"26:08:00","headsign":"Aarhus Rutebilstation"},{"route_id":"102785-23966_3","trip_id":"102785-159635964","short_name":"113","arrival":"26:07:00","departure":"26:07:00","headsign":"Aarhus Rutebilstation"}],"102785-000703001202":[{"route_id":"102785-23966_3","trip_id":"102785-159350476","short_name":"113","arrival":"26:08:30","departure":"26:08:30","headsign":"Aarhus Rutebilstation"},{"route_id":"102785-23966_3","trip_id":"102785-159635964","short_name":"113","arrival":"26:07:30","departure":"26:07:30","headsign":"Aarhus Rutebilstation"}],"102785-000703001212":[{"route_id":"102785-23966_3","trip_id":"102785-159350476","short_name":"113","arrival":"26:09:00","departure":"26:09:00","headsign":"Aarhus Rutebilstation"},{"route_id":"102785-23966_3","trip_id":"102785-159635964","short_name":"113","arrival":"26:08:00","departure":"26:08:00","headsign":"Aarhus Rutebilstation"}],"102785-000703003002":[{"route_id":"102785-23966_3","trip_id":"102785-159350476","short_name":"113","arrival":"26:09:30","departure":"26:09:30","headsign":"Aarhus Rutebilstation"},{"route_id":"102785-23966_3","trip_id":"102785-159635964","short_name":"113","arrival":"26:08:30","departure":"26:08:30","headsign":"Aarhus Rutebilstation"}],"102785-000703001712":[{"route_id":"102785-23966_3","trip_id":"102785-159635964","short_name":"113","arrival":"26:09:00","departure":"26:09:00","headsign":"Aarhus Rutebilstation"}],"102785-000733000132":[{"route_id":"102785-23939_3","trip_id":"102785-159349004","short_name":"100","arrival":"26:05:00","departure":"26:05:00","headsign":"Odder Busterminal"}],"102785-000733001909":[{"route_id":"102785-23939_3","trip_id":"102785-159349004","short_name":"100","arrival":"26:05:30","departure":"26:05:30","headsign":"Odder Busterminal"}],"102785-000733001912":[{"route_id":"102785-23939_3","trip_id":"102785-159349004","short_name":"100","arrival":"26:06:00","departure":"26:06:00","headsign":"Odder Busterminal"}],"102785-000733001702":[{"route_id":"102785-23939_3","trip_id":"102785-159349004","short_name":"100","arrival":"26:07:00","departure":"26:07:00","headsign":"Odder Busterminal"}],"102785-000733002202":[{"route_id":"102785-23939_3","trip_id":"102785-159349004","short_name":"100","arrival":"26:08:00","departure":"26:08:00","headsign":"Odder Busterminal"}],"102785-000733002102":[{"route_id":"102785-23939_3","trip_id":"102785-159349004","short_name":"100","arrival":"26:08:30","departure":"26:08:30","headsign":"Odder Busterminal"}],"102785-000733000512":[{"route_id":"102785-23939_3","trip_id":"102785-159349004","short_name":"100","arrival":"26:09:00","departure":"26:09:00","headsign":"Odder Busterminal"}],"102785-000008608719":[{"route_id":"102785-25479_0","trip_id":"102785-155468560","short_name":"L","arrival":"26:06:00","departure":"26:06:00","headsign":"Parkering Odense Syd"},{"route_id":"102785-25479_0","trip_id":"102785-155468559","short_name":"L","arrival":"26:06:00","departure":"26:06:00","headsign":"Parkering Odense Syd"}],"102785-000407018401":[{"route_id":"102785-25782_3","trip_id":"102785-155829350","short_name":"6 N","arrival":"26:05:00","departure":"26:05:00","headsign":"Vestermarie-Aakirkeby-Snogebæk-Svaneke-Rønne"},{"route_id":"102785-25782_3","trip_id":"102785-155829351","short_name":"6 N","arrival":"26:05:00","departure":"26:05:00","headsign":"Vestermarie-Aakirkeby-Snogebæk-Svaneke-Rønne"}],"102785-000407017301":[{"route_id":"102785-25782_3","trip_id":"102785-155829350","short_name":"6 N","arrival":"26:06:00","departure":"26:06:00","headsign":"Vestermarie-Aakirkeby-Snogebæk-Svaneke-Rønne"},{"route_id":"102785-25782_3","trip_id":"102785-155829351","short_name":"6 N","arrival":"26:06:00","departure":"26:06:00","headsign":"Vestermarie-Aakirkeby-Snogebæk-Svaneke-Rønne"}],"102785-000407018801":[{"route_id":"102785-25782_3","trip_id":"102785-155829350","short_name":"6 N","arrival":"26:07:00","departure":"26:07:00","headsign":"Vestermarie-Aakirkeby-Snogebæk-Svaneke-Rønne"},{"route_id":"102785-25782_3","trip_id":"102785-155829351","short_name":"6 N","arrival":"26:07:00","departure":"26:07:00","headsign":"Vestermarie-Aakirkeby-Snogebæk-Svaneke-Rønne"}],"102785-000407000501":[{"route_id":"102785-25782_3","trip_id":"102785-155829350","short_name":"6 N","arrival":"26:08:00","departure":"26:08:00","headsign":"Vestermarie-Aakirkeby-Snogebæk-Svaneke-Rønne"},{"route_id":"102785-25782_3","trip_id":"102785-155829351","short_name":"6 N","arrival":"26:08:00","departure":"26:08:00","headsign":"Vestermarie-Aakirkeby-Snogebæk-Svaneke-Rønne"}],"102785-000409010401":[{"route_id":"102785-25779_3","trip_id":"102785-155829347","short_name":"1 N","arrival":"26:05:00","departure":"26:05:00","headsign":"Klemensker-Allinge-Gudhjem-Rønne"},{"route_id":"102785-25779_3","trip_id":"102785-155829348","short_name":"1 N","arrival":"26:05:00","departure":"26:05:00","headsign":"Klemensker-Allinge-Gudhjem-Rønne"}],"102785-000409010101":[{"route_id":"102785-25779_3","trip_id":"102785-155829347","short_name":"1 N","arrival":"26:06:00","departure":"26:06:00","headsign":"Klemensker-Allinge-Gudhjem-Rønne"},{"route_id":"102785-25779_3","trip_id":"102785-155829348","short_name":"1 N","arrival":"26:06:00","departure":"26:06:00","headsign":"Klemensker-Allinge-Gudhjem-Rønne"}],"102785-000409000301":[{"route_id":"102785-25779_3","trip_id":"102785-155829347","short_name":"1 N","arrival":"26:07:00","departure":"26:07:00","headsign":"Klemensker-Allinge-Gudhjem-Rønne"},{"route_id":"102785-25779_3","trip_id":"102785-155829348","short_name":"1 N","arrival":"26:07:00","departure":"26:07:00","headsign":"Klemensker-Allinge-Gudhjem-Rønne"}],"102785-000000042738":[{"route_id":"102785-25129_3","trip_id":"102785-159464086","short_name":"710r","arrival":"26:08:00","departure":"26:08:00","headsign":"Nykøbing F St."}],"102785-000000040881":[{"route_id":"102785-25129_3","trip_id":"102785-159464004","short_name":"710r","arrival":"26:07:00","departure":"26:07:00","headsign":"Grænge St"}],"102785-000008602619":[{"route_id":"102785-24603_2","trip_id":"102785-159229975","short_name":"710r","arrival":"26:05:00","departure":"26:07:00","headsign":"Nakskov"},{"route_id":"102785-24603_2","trip_id":"102785-159229991","short_name":"710r","arrival":"26:05:00","departure":"26:07:00","headsign":"Nakskov"}],"102785-000008600683":[{"route_id":"102785-24492_2","trip_id":"102785-159231348","short_name":"950r","arrival":"26:06:00","departure":"26:06:00","headsign":"Hillerød"},{"route_id":"102785-24489_2","trip_id":"102785-159230795","short_name":"920r","arrival":"26:07:00","departure":"26:07:00","headsign":"Hillerød"}],"102785-000008601615":[{"route_id":"102785-24491_2","trip_id":"102785-159231189","short_name":"940r","arrival":"26:05:00","departure":"26:05:00","headsign":"Helsingør"}],"102785-000008601625":[{"route_id":"102785-24491_2","trip_id":"102785-159231163","short_name":"940r","arrival":"26:06:00","departure":"26:06:00","headsign":"Gilleleje"}],"102785-000008601620":[{"route_id":"102785-24491_2","trip_id":"102785-159231163","short_name":"940r","arrival":"26:07:00","departure":"26:07:00","headsign":"Gilleleje"}],"102785-000008600668":[{"route_id":"102785-24490_2","trip_id":"102785-159230888","short_name":"930r","arrival":"26:05:00","departure":"26:06:00","headsign":"Hillerød"}],"102785-000008600779":[{"route_id":"102785-24490_2","trip_id":"102785-159230888","short_name":"930r","arrival":"26:09:00","departure":"26:09:00","headsign":"Hillerød"}],"102785-000008601721":[{"route_id":"102785-24489_2","trip_id":"102785-159230670","short_name":"920r","arrival":"26:07:00","departure":"26:07:00","headsign":"Hundested"}],"102785-000000005320":[{"route_id":"102785-7437_700","trip_id":"102785-159458902","short_name":"600s","arrival":"26:05:00","departure":"26:05:00","headsign":"Ishøj St."}],"102785-000000005321":[{"route_id":"102785-7437_700","trip_id":"102785-159458902","short_name":"600s","arrival":"26:06:00","departure":"26:06:00","headsign":"Ishøj St."}],"102785-000000008964":[{"route_id":"102785-7437_700","trip_id":"102785-159458902","short_name":"600s","arrival":"26:07:00","departure":"26:07:00","headsign":"Ishøj St."}],"102785-000000005123":[{"route_id":"102785-7437_700","trip_id":"102785-159458902","short_name":"600s","arrival":"26:09:00","departure":"26:09:00","headsign":"Ishøj St."}],"102785-000000005907":[{"route_id":"102785-7437_700","trip_id":"102785-159458713","short_name":"600s","arrival":"26:06:00","departure":"26:06:00","headsign":"Hillerød St."},{"route_id":"102785-7437_700","trip_id":"102785-159458787","short_name":"600s","arrival":"26:08:00","departure":"26:08:00","headsign":"Hillerød St."}],"102785-000000005905":[{"route_id":"102785-7437_700","trip_id":"102785-159458787","short_name":"600s","arrival":"26:05:00","departure":"26:05:00","headsign":"Hillerød St."}],"102785-000000000879":[{"route_id":"102785-7393_3","trip_id":"102785-159446051","short_name":"36","arrival":"26:05:00","departure":"26:05:00","headsign":"Vestamager Nøragersmindevej"},{"route_id":"102785-7393_3","trip_id":"102785-159446050","short_name":"36","arrival":"26:05:00","departure":"26:05:00","headsign":"Vestamager Nøragersmindevej"}],"102785-000000000880":[{"route_id":"102785-7393_3","trip_id":"102785-159446051","short_name":"36","arrival":"26:06:00","departure":"26:06:00","headsign":"Vestamager Nøragersmindevej"},{"route_id":"102785-7393_3","trip_id":"102785-159446050","short_name":"36","arrival":"26:06:00","departure":"26:06:00","headsign":"Vestamager Nøragersmindevej"}]}