{"102785-000007400003":[{"route_id":"102785-25734_3","trip_id":"102785-159569618","short_name":"6802","arrival":"28:15:00","departure":"28:15:00","headsign":"Malmö C"}],"102785-000008600502":[{"route_id":"102785-26550_2","trip_id":"102785-159587797","short_name":"Rj","arrival":"28:16:00","departure":"28:16:00","headsign":"København H"},{"route_id":"102785-26550_2","trip_id":"102785-159587795","short_name":"Rj","arrival":"28:19:00","departure":"28:19:00","headsign":"København H"},{"route_id":"102785-26550_2","trip_id":"102785-159587798","short_name":"Rj","arrival":"28:19:00","departure":"28:19:00","headsign":"København H"},{"route_id":"102785-26550_2","trip_id":"102785-159587796","short_name":"Rj","arrival":"28:16:00","departure":"28:16:00","headsign":"København H"},{"route_id":"102785-26550_2","trip_id":"102785-159587794","short_name":"Rj","arrival":"28:19:00","departure":"28:19:00","headsign":"København H"}],"102785-000008600503":[{"route_id":"102785-26550_2","trip_id":"102785-159587797","short_name":"Rj","arrival":"28:18:00","departure":"28:18:00","headsign":"København H"},{"route_id":"102785-26550_2","trip_id":"102785-159587796","short_name":"Rj","arrival":"28:18:00","departure":"28:18:00","headsign":"København H"}],"102785-000008600501":[{"route_id":"102785-26550_2","trip_id":"102785-159587795","short_name":"Rj","arrival":"28:13:00","departure":"28:15:00","headsign":"København H"},{"route_id":"102785-26550_2","trip_id":"102785-159587798","short_name":"Rj","arrival":"28:13:00","departure":"28:15:00","headsign":"København H"},{"route_id":"102785-26550_2","trip_id":"102785-159587794","short_name":"Rj","arrival":"28:13:00","departure":"28:15:00","headsign":"København H"}],"102785-000008600048":[{"route_id":"102785-23839_3","trip_id":"102785-159581051","short_name":"Rød","arrival":"28:16:00","departure":"28:16:00","headsign":"Aarhus H (togbus)"}],"102785-000008600683":[{"route_id":"102785-16448_109","trip_id":"102785-159166909","short_name":"A","arrival":"28:15:00","departure":"28:15:00","headsign":"Hillerød St."}],"102785-000407106301":[{"route_id":"102785-25782_3","trip_id":"102785-155829352","short_name":"6 N","arrival":"28:16:00","departure":"28:16:00","headsign":"Vestermarie-Aakirkeby-Snogebæk-Svaneke-Rønne"},{"route_id":"102785-25779_3","trip_id":"102785-155829345","short_name":"1 N","arrival":"28:16:00","departure":"28:16:00","headsign":"Klemensker-Allinge-Gudhjem-Rønne"}],"102785-000407000601":[{"route_id":"102785-25782_3","trip_id":"102785-155829352","short_name":"6 N","arrival":"28:17:00","departure":"28:17:00","headsign":"Vestermarie-Aakirkeby-Snogebæk-Svaneke-Rønne"},{"route_id":"102785-25779_3","trip_id":"102785-155829345","short_name":"1 N","arrival":"28:18:00","departure":"28:18:00","headsign":"Klemensker-Allinge-Gudhjem-Rønne"}],"102785-000407105101":[{"route_id":"102785-25782_3","trip_id":"102785-155829352","short_name":"6 N","arrival":"28:18:00","departure":"28:18:00","headsign":"Vestermarie-Aakirkeby-Snogebæk-Svaneke-Rønne"},{"route_id":"102785-25779_3","trip_id":"102785-155829345","short_name":"1 N","arrival":"28:19:00","departure":"28:19:00","headsign":"Klemensker-Allinge-Gudhjem-Rønne"}]}